guanciale/__init__.py
guanciale/config.py
guanciale/core.py
guanciale/errors.py
guanciale/idascript.py
guanciale/idblib.py
guanciale/matching.py
guanciale/status.py
guanciale-1.0.20.dist-info/DESCRIPTION.rst
guanciale-1.0.20.dist-info/METADATA
guanciale-1.0.20.dist-info/RECORD
guanciale-1.0.20.dist-info/WHEEL
guanciale-1.0.20.dist-info/metadata.json
guanciale-1.0.20.dist-info/top_level.txt
