Metadata-Version: 2.0
Name: guanciale
Version: 1.0.20
Summary: Grab information needed by Carbonara
Home-page: https://github.com/Carbonara-Project/Guanciale
Author: Andrea Fioraldi, Luigi Paolo Pileggi
Author-email: andreafioraldi@gmail.com, rop2bash@gmail.com
License: BSD 2-clause
Download-URL: https://github.com/Carbonara-Project/Guanciale/archive/1.0.20.tar.gz
Platform: UNKNOWN
Requires-Dist: requests
Requires-Dist: carbonara-idb
Requires-Dist: carbonara-archinfo
Requires-Dist: carbonara-pyvex
Requires-Dist: appdirs
Requires-Dist: datasketch
Requires-Dist: r2pipe
